.gitignore
CHANGES.rst
MANIFEST.in
README.rst
bootstrap.py
buildout.cfg
setup.py
archetypes/__init__.py
archetypes.querywidget.egg-info/PKG-INFO
archetypes.querywidget.egg-info/SOURCES.txt
archetypes.querywidget.egg-info/dependency_links.txt
archetypes.querywidget.egg-info/entry_points.txt
archetypes.querywidget.egg-info/namespace_packages.txt
archetypes.querywidget.egg-info/not-zip-safe
archetypes.querywidget.egg-info/requires.txt
archetypes.querywidget.egg-info/top_level.txt
archetypes/querywidget/__init__.py
archetypes/querywidget/configure.zcml
archetypes/querywidget/field.py
archetypes/querywidget/interfaces.py
archetypes/querywidget/querywidget.css
archetypes/querywidget/querywidget.js
archetypes/querywidget/views.py
archetypes/querywidget/widget.py
archetypes/querywidget/profiles/default/cssregistry.xml
archetypes/querywidget/profiles/default/jsregistry.xml
archetypes/querywidget/profiles/default/metadata.xml
archetypes/querywidget/profiles/default/skins.xml
archetypes/querywidget/profiles/test_fixture/metadata.xml
archetypes/querywidget/profiles/test_fixture/registry.xml
archetypes/querywidget/skins/querywidget/querywidget.pt
archetypes/querywidget/templates/date_range_widget.pt
archetypes/querywidget/templates/date_widget.pt
archetypes/querywidget/templates/empty_widget.pt
archetypes/querywidget/templates/multiple_selection_widget.pt
archetypes/querywidget/templates/reference_widget.pt
archetypes/querywidget/templates/relative_date_widget.pt
archetypes/querywidget/templates/relative_path_widget.pt
archetypes/querywidget/templates/remove_criteria_link.pt
archetypes/querywidget/templates/string_widget.pt
archetypes/querywidget/tests/__init__.py
archetypes/querywidget/tests/base.py
archetypes/querywidget/tests/integration.rst
archetypes/querywidget/tests/test_integration_doctest.py
archetypes/querywidget/tests/test_multi_select_widget.py
archetypes/querywidget/tests/javascripts/README.txt
archetypes/querywidget/tests/javascripts/jquery-1.7.2.min.js
archetypes/querywidget/tests/javascripts/jquery-1.8.3.min.js
archetypes/querywidget/tests/javascripts/jquery-1.9.1.min.js
archetypes/querywidget/tests/javascripts/querywidget.js
archetypes/querywidget/tests/javascripts/test_querywidget.html
archetypes/querywidget/tests/javascripts/test_querywidget_1.8.html
archetypes/querywidget/tests/javascripts/test_querywidget_1.9.html
