Metadata-Version: 1.1
Name: archetypes.querywidget
Version: 1.1.1
Summary: Archetypes.querywidget implements a widget for creating catalog queries using an email-filtering-like interface, as found in GMail or Apple Mail.
Home-page: http://pypi.python.org/pypi/archetypes.querywidget
Author: Plone Foundation
Author-email: plone-developers@lists.sourceforge.net
License: GPL version 2
Platform: UNKNOWN
Classifier: Framework :: Plone
Classifier: License :: OSI Approved :: GNU General Public License (GPL)
Classifier: Programming Language :: Python
